[{"nId":0,"id":"add_silver_1K","itemName":"1K\u94F6\u5E01","persContr":7500,"allianceContr":7500,"num":1000,"allianceLv":1},{"nId":1,"id":"res_khorium_1K","itemName":"1K\u6C2A\u6676","persContr":75000,"allianceContr":75000,"num":1000,"allianceLv":1},{"nId":2,"id":"food_consume25P_red_24H","itemName":"\u521D\u7EA7\u519B\u8D39\u7F29\u51CF24H","persContr":75000,"allianceContr":75000,"num":100,"allianceLv":1},{"nId":3,"id":"food_produce_add","itemName":"\u98DF\u54C1\u5382\u589E\u4EA7","persContr":4500,"allianceContr":4500,"num":1000,"allianceLv":1},{"nId":4,"id":"metal_produce_add","itemName":"\u51B6\u70BC\u5382\u589E\u4EA7","persContr":4500,"allianceContr":4500,"num":1000,"allianceLv":1},{"nId":5,"id":"oil_produce_add","itemName":"\u70BC\u6CB9\u5382\u589E\u4EA7","persContr":7500,"allianceContr":7500,"num":1000,"allianceLv":2},{"nId":6,"id":"alloy_produce_add","itemName":"\u5408\u91D1\u5382\u589E\u4EA7","persContr":10500,"allianceContr":10500,"num":1000,"allianceLv":3},{"nId":7,"id":"userArmy_resetting","itemName":"\u5175\u79CD\u91CD\u7F6E\u5361","persContr":150000,"allianceContr":75000,"num":100,"allianceLv":1},{"nId":8,"id":"def_add_12H","itemName":"12H\u9632\u5FA1\u63D0\u5347","persContr":37500,"allianceContr":37500,"num":1000,"allianceLv":1},{"nId":9,"id":"atk_add_12H","itemName":"12H\u706B\u529B\u63D0\u5347","persContr":37500,"allianceContr":37500,"num":1000,"allianceLv":1},{"nId":10,"id":"war_protect_8H","itemName":"8H\u6218\u4E89\u4FDD\u62A4","persContr":75000,"allianceContr":75000,"num":100,"allianceLv":1},{"nId":11,"id":"vip_100P","itemName":"100 VIP\u70B9\u6570","persContr":22500,"allianceContr":22500,"num":100,"allianceLv":2},{"nId":12,"id":"userSkill_resetting","itemName":"\u6280\u80FD\u91CD\u7F6E\u5361","persContr":150000,"allianceContr":150000,"num":100,"allianceLv":1},{"nId":13,"id":"add_gem_5","itemName":"5\u91D1\u7B79\u7801","persContr":15000,"allianceContr":15000,"num":100,"allianceLv":1},{"nId":14,"id":"collectSpeed_8H","itemName":"8H\u91C7\u96C6\u52A0\u901F","persContr":90000,"allianceContr":90000,"num":1000,"allianceLv":1},{"nId":15,"id":"add_copper_3000","itemName":"3K\u94F6\u7B79\u7801","persContr":4500,"allianceContr":4500,"num":1000,"allianceLv":1},{"nId":16,"id":"recall_troops_low","itemName":"\u666E\u901A\u90E8\u7F72\u53EC\u56DE","persContr":7500,"allianceContr":7500,"num":100,"allianceLv":2},{"nId":17,"id":"acc_12H","itemName":"12H\u52A0\u901F","persContr":142500,"allianceContr":142500,"num":50,"allianceLv":3},{"nId":18,"id":"acc_1H","itemName":"1H\u52A0\u901F","persContr":22500,"allianceContr":22500,"num":200,"allianceLv":2},{"nId":19,"id":"acc_5M","itemName":"5M\u52A0\u901F","persContr":2200,"allianceContr":2200,"num":1000,"allianceLv":1}]