[{"nId":0,"id":"kindomBuild_0003","iconId":"taskIcon_war","TaskName":"mainTask_name_Hospital","TaskDescription":"mainTask_des_Hospital%1","CompleteConditon":["taskTrain('uid','Conscript','150')"],"RewardList":["food:1","metal:10","oil:10","alloy:100"],"TaskType":0,"Process":10,"ModuleType":3},{"nId":1,"id":"kindomBuild_0002","iconId":"taskIcon_war","TaskName":"mainTask_name_Hospital","TaskDescription":"mainTask_des_Hospital%1","CompleteConditon":["taskResearch('uid','123','1')"],"RewardList":["food:1","metal:10","oil:10","alloy:100"],"TaskType":0,"Process":10,"ModuleType":2},{"nId":2,"id":"kindomBuild_0001","iconId":"taskIcon_war","TaskName":"mainTask_name_Hospital","TaskDescription":"mainTask_des_Hospital%1","CompleteConditon":["taskBuild('uid','TechCenter','1')"],"RewardList":["food:1","metal:10","oil:10","alloy:100"],"TaskType":0,"Process":10,"ModuleType":1},{"nId":3,"id":"kindomBuild_0004","iconId":"taskIcon_war","TaskName":"mainTask_name_Hospital","TaskDescription":"mainTask_des_Hospital%1","CompleteConditon":["taskAllianceLevel('uid','1')"],"RewardList":["food:1","metal:10","oil:10","alloy:100"],"TaskType":0,"Process":10,"ModuleType":17}]